openoperator/README.md
openoperator/__init__.py
openoperator/llm.py
openoperator/logging_config.py
openoperator/utils.py
openoperator/agent/prompts.py
openoperator/agent/service.py
openoperator/agent/views.py
openoperator/agent/message_manager/service.py
openoperator/agent/message_manager/views.py
openoperator/agent/task_manager/service.py
openoperator/browser/browser.py
openoperator/browser/context.py
openoperator/browser/views.py
openoperator/controller/service.py
openoperator/controller/views.py
openoperator/controller/registry/service.py
openoperator/controller/registry/views.py
openoperator/dom/__init__.py
openoperator/dom/buildDomTree.js
openoperator/dom/service.py
openoperator/dom/views.py
openoperator/dom/history_tree_processor/service.py
openoperator/dom/history_tree_processor/view.py
openoperator/telemetry/service.py
openoperator/telemetry/views.py
openoperator-0.1.4.dist-info/METADATA
openoperator-0.1.4.dist-info/WHEEL
openoperator-0.1.4.dist-info/licenses/LICENSE
openoperator-0.1.4.dist-info/RECORD
