Metadata-Version: 2.4
Name: openoperator
Version: 0.1.4
Summary: Operate any browser, desktop, device or robot.
Author: Kevin Raetz
License-File: LICENSE
Classifier: License :: OSI Approved :: MIT License
Classifier: Operating System :: OS Independent
Classifier: Programming Language :: Python :: 3
Requires-Python: <4.0,>=3.11
Requires-Dist: beautifulsoup4==4.12.3
Requires-Dist: httpx==0.28.1
Requires-Dist: langchain-anthropic==0.3.3
Requires-Dist: langchain-aws==0.2.11
Requires-Dist: langchain-deepseek-official==0.1.0
Requires-Dist: langchain-fireworks==0.2.6
Requires-Dist: langchain-google-genai==2.0.8
Requires-Dist: langchain-google-vertexai==2.0.12
Requires-Dist: langchain-groq==0.2.3
Requires-Dist: langchain-huggingface>=0.1.2
Requires-Dist: langchain-ollama==0.2.2
Requires-Dist: langchain-openai==0.3.2
Requires-Dist: langchain-together>=0.3.0
Requires-Dist: langchain==0.3.14
Requires-Dist: lmnr[langchain]==0.4.56
Requires-Dist: maincontentextractor==0.0.4
Requires-Dist: playwright==1.49.1
Requires-Dist: posthog==3.11.0
Requires-Dist: pydantic==2.10.6
Requires-Dist: python-dotenv==1.0.1
Requires-Dist: requests==2.32.3
Requires-Dist: setuptools==75.8.0
Requires-Dist: tld==0.13
Provides-Extra: dev
Requires-Dist: black==24.10.0; extra == 'dev'
Requires-Dist: build==1.2.2; extra == 'dev'
Requires-Dist: hatch==1.13.0; extra == 'dev'
Requires-Dist: pytest-asyncio==0.24.0; extra == 'dev'
Requires-Dist: pytest==8.3.3; extra == 'dev'
Requires-Dist: tokencost==0.1.16; extra == 'dev'
Provides-Extra: examples
Requires-Dist: discord==2.3.2; extra == 'examples'
Requires-Dist: fastapi>=0.115.7; extra == 'examples'
Requires-Dist: pypdf2==3.0.1; extra == 'examples'
Requires-Dist: slack-sdk>=3.34.0; extra == 'examples'
Requires-Dist: uvicorn>=0.34.0; extra == 'examples'
